{
  "player_status": {
    "energy": "4/3",
    "health": "45/80",
    "block": 0,
    "statuses": {},
    "hand": []
  },
  "enemies": [
    {
      "name": "monster1",
      "health": "None",
      "block": 0,
      "intent": "Aggressive This enemy intends to Attack for22 damage",
      "statuses": {
        "msg1": "Vulnerable Receive 50% more damage from Attacks for 1turn.",
        "msg2": "Ritual At the end ofits turn, gains 4 Strength",
        "msg3": "Strength Increases attack damage by16."
      }
    }
  ]
}